planar_magnetics/__init__.py
planar_magnetics/creepage.py
planar_magnetics/geometry.py
planar_magnetics/kicad.py
planar_magnetics/materials.py
planar_magnetics/smoothing.py
planar_magnetics/utils.py
planar_magnetics/cores/__init__.py
planar_magnetics/cores/cores.py
planar_magnetics/inductors/__init__.py
planar_magnetics/inductors/cffc.py
planar_magnetics/transformers/__init__.py
planar_magnetics/transformers/transformers.py
planar_magnetics/windings/__init__.py
planar_magnetics/windings/single.py
planar_magnetics/windings/spirals.py
planar_magnetics/windings/windings.py
planar_magnetics-0.1.6.dist-info/LICENSE
planar_magnetics-0.1.6.dist-info/METADATA
planar_magnetics-0.1.6.dist-info/WHEEL
planar_magnetics-0.1.6.dist-info/top_level.txt
planar_magnetics-0.1.6.dist-info/RECORD
