Metadata-Version: 2.1
Name: planar-magnetics
Version: 0.1.6
Summary: Create planar magnetic structures programmatically and export to CAD tools.
Home-page: https://github.com/dzimmanck/python-planar-magnetics
Author: Donny Zimmanck
Author-email: dzimmanck@gmail.com
License: UNKNOWN
Project-URL: Bug Tracker, https://github.com/dzimmanck/python-planar-magnetics/issues
Platform: UNKNOWN
Classifier: Development Status :: 3 - Alpha
Classifier: Programming Language :: Python :: 3
Classifier: License :: OSI Approved :: Apache Software License
Classifier: Operating System :: OS Independent
Requires-Python: >=3.7
License-File: LICENSE
Requires-Dist: ezdxf (>=0.17.2)
Provides-Extra: dev
Requires-Dist: pytest ; extra == 'dev'
